{
  "name": "Sue Howard",
  "age": 37,
  "address": {
    "street": "Durog Extension",
    "city": "Pijotef",
    "state": "LA",
    "zip": "99825"
  },
  "contact": {
    "phone": "(615) 675-3110",
    "servicePhone": "800764465"
  },
  "birthday": "1993-08-15T08:12:38.348Z",
  "ip": "116.67.41.197",
  "foo": "bar",
  "profile": {
    "about": "Gigzajo fuhihac kijke fesisa row mewamol vokios nuowese humulaf kup kof pofacde ecwimgut sume laduf ukjioco. Badegsor ried zilzuhi owipesa ful dum zuvuli akwitiji ik uv val gi og awtumis cegdodo ado ham mifhiv. Tojafpez itcam omilu gab ifumir gajtim hok vuv muezmi cocze og nechu mec gawor. Fikhojro asu zintu jaloh jizrug zo nulmidud cuf ofeciv tu zome kavdune it hov nurawwo. Febupsug uvujo hi fe mufgev cege jigjigfe iriho pufuh kidzejnac mudpoka feh likpil tigesho vutedov dojug.",
    "bio": "Za abe zuzgo lukgaiki cumihisi eh it ru docjurcil joc col lat puw ho kusosbob ega laej af. Hodor du haj sesujez dozet iw eta fatas wac wudar rep zidneb. Na nir wuh se uwo oha foh vam vozuj kejeig ihkegiz wifipoko. Pomepa vuwlurda opisuh alohacob ijiput kebo ijenele sa la zaf bi nugowali adoop. Filnuze jehipmi wibij posifa wi jad edpa opogur ahaliwin papezjes saptaese ro vubra irifow pado vodapoim egujujem."
  },
  "apiKey": "3ef4b769c33c05425658b2e39babb7cd8974bcfc6be15205b332f32989d88a5c",
  "currency": {
    "code": "ZMW",
    "name": "Zambia Kwacha"
  }
}